sunslack.py
sunslack-1.1.3.dist-info/LICENSE
sunslack-1.1.3.dist-info/METADATA
sunslack-1.1.3.dist-info/WHEEL
sunslack-1.1.3.dist-info/entry_points.txt
sunslack-1.1.3.dist-info/top_level.txt
sunslack-1.1.3.dist-info/RECORD
