Metadata-Version: 2.1
Name: sunslack
Version: 1.1.3
Summary: Slack bot publishing NOAA Solar data
Home-page: https://0x9900.com/
Author: Fred C. (W6BSD)
Author-email: w6bsd@bsdworld.org
License: BSD
Project-URL: Source, https://github.com/0x9900/sun-slack/
Project-URL: Tracker, https://github.com/0x9900/sun-slack/issues
Platform: UNKNOWN
Classifier: Development Status :: 3 - Alpha
Classifier: Intended Audience :: Developers
Classifier: License :: OSI Approved :: BSD License
Classifier: Operating System :: OS Independent
Classifier: Programming Language :: Python
Classifier: Programming Language :: Python :: 3
Classifier: Programming Language :: Python :: 3.6
Classifier: Programming Language :: Python :: 3.7
Classifier: Programming Language :: Python :: 3.8
Classifier: Topic :: Communications :: Ham Radio
Requires-Python: >=3.6.0
License-File: LICENSE
Requires-Dist: matplotlib
Requires-Dist: slack-sdk
